odoo/addons/shopinvader_product_seasonality_search_engine/README.rst
odoo/addons/shopinvader_product_seasonality_search_engine/__init__.py
odoo/addons/shopinvader_product_seasonality_search_engine/__manifest__.py
odoo/addons/shopinvader_product_seasonality_search_engine/components/__init__.py
odoo/addons/shopinvader_product_seasonality_search_engine/components/seasonal_config_line_event_listener.py
odoo/addons/shopinvader_product_seasonality_search_engine/i18n/shopinvader_product_seasonality_search_engine.pot
odoo/addons/shopinvader_product_seasonality_search_engine/models/__init__.py
odoo/addons/shopinvader_product_seasonality_search_engine/models/seasonal_config_line.py
odoo/addons/shopinvader_product_seasonality_search_engine/models/shopinvader_seasonal_config_line.py
odoo/addons/shopinvader_product_seasonality_search_engine/readme/CONTRIBUTORS.rst
odoo/addons/shopinvader_product_seasonality_search_engine/readme/DESCRIPTION.rst
odoo/addons/shopinvader_product_seasonality_search_engine/static/description/index.html
odoo/addons/shopinvader_product_seasonality_search_engine/tests/__init__.py
odoo/addons/shopinvader_product_seasonality_search_engine/tests/test_prod_seasonality.py
odoo/addons/shopinvader_product_seasonality_search_engine/views/shopinvader_seasonal_config.xml
odoo14_addon_shopinvader_product_seasonality_search_engine-14.0.1.0.1.dist-info/METADATA
odoo14_addon_shopinvader_product_seasonality_search_engine-14.0.1.0.1.dist-info/WHEEL
odoo14_addon_shopinvader_product_seasonality_search_engine-14.0.1.0.1.dist-info/top_level.txt
odoo14_addon_shopinvader_product_seasonality_search_engine-14.0.1.0.1.dist-info/RECORD
